[{"line":3,"elements":[{"start_timestamp":"2025-06-24T06:50:15.914Z","before":[{"result":{"duration":6253000000,"status":"passed"},"match":{"location":"Testing.stepDefs.Hooks.setupDriver()"}}],"line":44,"name":"user should be able to add items in amazon","description":"","id":"amazon;user-should-be-able-to-add-items-in-amazon;;2","after":[{"result":{"status":"passed"},"match":{"location":"Testing.stepDefs.Hooks.quitDriver()"}}],"type":"scenario","keyword":"Scenario Outline","steps":[{"result":{"duration":6138000000,"status":"passed"},"line":6,"name":"user navigate to amazon EG","match":{"location":"Testing.stepDefs.amazonHomeStepDef.userNavigateToGoogle()"},"keyword":"Given "},{"result":{"duration":1110000000,"status":"passed"},"line":7,"name":"user click on sign in","match":{"location":"Testing.stepDefs.amazonHomeStepDef.userClickOnSignIn()"},"keyword":"Given "},{"result":{"duration":160000000,"status":"passed"},"line":8,"name":"user insert phone number \"+4915755457595\"","match":{"arguments":[{"val":"\"+4915755457595\"","offset":25}],"location":"Testing.stepDefs.loginStepDef.userInsertPhoneNumber(java.lang.String)"},"keyword":"And "},{"result":{"duration":1760000000,"status":"passed"},"line":9,"name":"user clicks continue","match":{"location":"Testing.stepDefs.loginStepDef.userClicksContinue()"},"keyword":"And "},{"result":{"duration":92000000,"status":"passed"},"line":10,"name":"user insert password \"@Desha0097\"","match":{"arguments":[{"val":"\"@Desha0097\"","offset":21}],"location":"Testing.stepDefs.loginStepDef.userInsertPassword(java.lang.String)"},"keyword":"And "},{"result":{"duration":133000000,"status":"passed"},"line":11,"name":"user clicks sign in","match":{"location":"Testing.stepDefs.loginStepDef.userClicksSignIn()"},"keyword":"And "},{"result":{"duration":2646000000,"status":"passed"},"line":12,"name":"user clicks on all side menu","match":{"location":"Testing.stepDefs.amazonHomeStepDef.userTypesInGoogleSearchBar()"},"keyword":"When "},{"result":{"duration":662000000,"status":"passed"},"line":13,"name":"user clicks on see all","match":{"location":"Testing.stepDefs.amazonHomeStepDef.userClicksOnSeeAll()"},"keyword":"And "},{"result":{"duration":311000000,"status":"passed"},"line":14,"name":"user clicks on video games \"Video Games\"","match":{"arguments":[{"val":"\"Video Games\"","offset":27}],"location":"Testing.stepDefs.amazonHomeStepDef.userClicksOnVideoGames(java.lang.String)"},"keyword":"And "},{"result":{"duration":2832000000,"status":"passed"},"line":15,"name":"user clicks on all video games \"Xbox One\"","match":{"arguments":[{"val":"\"Xbox One\"","offset":31}],"location":"Testing.stepDefs.amazonHomeStepDef.userClicksOnAllVideoGames(java.lang.String)"},"keyword":"And "},{"result":{"status":"passed"},"line":16,"name":"user verifies that he is navigated to all video games page","match":{"location":"Testing.stepDefs.amazonHomeStepDef.userVerifiesThatHeIsNavigatedToAllVideoGamesPage()"},"keyword":"Then "},{"result":{"duration":1642000000,"status":"passed"},"line":17,"name":"user clicks on free shipping checkbox","match":{"location":"Testing.stepDefs.productsStepDef.userClicksOnFreeShippingCheckbox()"},"keyword":"When "},{"result":{"duration":1497000000,"status":"passed"},"line":18,"name":"user clicks on new condition","match":{"location":"Testing.stepDefs.productsStepDef.userClicksOnNewCondition()"},"keyword":"And "},{"result":{"duration":133000000,"status":"passed"},"line":19,"name":"user clicks on sort by dropdown list","match":{"location":"Testing.stepDefs.productsStepDef.userClicksOnSortByDropdownList()"},"keyword":"And "},{"result":{"duration":162000000,"status":"passed"},"line":20,"name":"user sorts by high to low price \"Price: Low to High\"","match":{"arguments":[{"val":"\"Price: Low to High\"","offset":32}],"location":"Testing.stepDefs.productsStepDef.userSortsByHighToLowPrice(java.lang.String)"},"keyword":"And "},{"result":{"duration":2737000000,"status":"passed"},"line":21,"name":"user randomly selects a product below 15000 and if not available he will click next page then repeat searching then clicks on cart to make sure that it's already added","match":{"arguments":[{"val":"15000","offset":38}],"location":"Testing.stepDefs.productsStepDef.userRandomlySelectAProductBelowPriceAndIfNotAvailableHeWillClickNextPageThenRepeatSearchingThenClicksOnCartToMakeSureThatIsTAlreadyAdded(int)"},"keyword":"And "},{"result":{"duration":1545000000,"status":"passed"},"line":22,"name":"user clicks on add to cart","match":{"location":"Testing.stepDefs.productsStepDef.userClicksOnAddToCart()"},"keyword":"And "},{"result":{"duration":37000000,"status":"passed"},"line":23,"name":"user should be navigated to cart page","match":{"location":"Testing.stepDefs.cartStepDef.userShouldBeNavigatedToCartPage()"},"keyword":"Then "},{"result":{"duration":16000000,"status":"passed"},"line":24,"name":"user validates that the cart isn't empty","match":{"location":"Testing.stepDefs.cartStepDef.userValidatesThatTheCartIsnTEmpty()"},"keyword":"And "},{"result":{"duration":24000000,"status":"passed"},"line":25,"name":"user validate that's proceed to buy is visible","match":{"location":"Testing.stepDefs.cartStepDef.userValidateThatSProceedToBuyIsVisible()"},"keyword":"And "},{"result":{"duration":2910000000,"status":"passed"},"line":26,"name":"user clicks on proceed to buy button","match":{"location":"Testing.stepDefs.cartStepDef.userClicksOnProceedToBuyButton()"},"keyword":"When "},{"result":{"duration":70000000,"status":"passed"},"line":27,"name":"user validates that value payment method is visible","match":{"location":"Testing.stepDefs.checkOutStepDef.userValidatesThatValuePaymentMethodIsVisible()"},"keyword":"Then "},{"result":{"duration":115000000,"status":"passed"},"line":28,"name":"user clicks on value payment method radio button","match":{"location":"Testing.stepDefs.checkOutStepDef.userClicksOnValuePaymentMethodRadioButton()"},"keyword":"When "},{"result":{"duration":49000000,"status":"passed"},"line":29,"name":"user validates that change delivery address is visible","match":{"location":"Testing.stepDefs.checkOutStepDef.userValidatesThatChangeDeliveryAddressIsVisible()"},"keyword":"Then "},{"result":{"duration":116000000,"status":"passed"},"line":30,"name":"user clicks on change delivery address button","match":{"location":"Testing.stepDefs.checkOutStepDef.userClicksOnChangeDeliveryAddressButton()"},"keyword":"When "},{"result":{"duration":2116000000,"status":"passed"},"line":31,"name":"add new delivery address button should be displayed","match":{"location":"Testing.stepDefs.checkOutStepDef.addNewDeliveryAddressButtonShouldBeDisplayed()"},"keyword":"Then "},{"result":{"duration":98000000,"status":"passed"},"line":32,"name":"user clicks on new delivery address button","match":{"location":"Testing.stepDefs.checkOutStepDef.userClicksOnNewDeliveryAddressButton()"},"keyword":"When "},{"result":{"duration":1148000000,"status":"passed"},"line":33,"name":"user insert full name \"mustafa\"","match":{"arguments":[{"val":"\"mustafa\"","offset":22}],"location":"Testing.stepDefs.checkOutStepDef.userInsertFullName(java.lang.String)"},"keyword":"And "},{"result":{"duration":107000000,"status":"passed"},"line":34,"name":"user insert full mobileNumber \"1063710097\"","match":{"arguments":[{"val":"\"1063710097\"","offset":30}],"location":"Testing.stepDefs.checkOutStepDef.userInsertFullMobileNumber(java.lang.String)"},"keyword":"And "},{"result":{"duration":76000000,"status":"passed"},"line":35,"name":"user insert street name \"test\"","match":{"arguments":[{"val":"\"test\"","offset":24}],"location":"Testing.stepDefs.checkOutStepDef.userInsertStreetName(java.lang.String)"},"keyword":"And "},{"result":{"duration":85000000,"status":"passed"},"line":36,"name":"user insert building name \"testing\"","match":{"arguments":[{"val":"\"testing\"","offset":26}],"location":"Testing.stepDefs.checkOutStepDef.userInsertBuildingName(java.lang.String)"},"keyword":"And "},{"result":{"duration":165000000,"status":"passed"},"line":37,"name":"user insert city \"cairo\"","match":{"arguments":[{"val":"\"cairo\"","offset":17}],"location":"Testing.stepDefs.checkOutStepDef.userInsertCity(java.lang.String)"},"keyword":"And "},{"result":{"duration":117000000,"status":"passed"},"line":38,"name":"user insert district \"Settlement)\"","match":{"arguments":[{"val":"\"Settlement)\"","offset":21}],"location":"Testing.stepDefs.checkOutStepDef.userInsertDistrict(java.lang.String)"},"keyword":"And "},{"result":{"duration":75000000,"status":"passed"},"line":39,"name":"user insert Governorate \"cairo\"","match":{"arguments":[{"val":"\"cairo\"","offset":24}],"location":"Testing.stepDefs.checkOutStepDef.userInsertGovernorate(java.lang.String)"},"keyword":"And "}],"tags":[{"name":"@UI"},{"name":"@test"}]}],"name":"amazon","description":"","id":"amazon","keyword":"Feature","uri":"file:src/main/resources/Testing/amazon.feature","tags":[{"name":"@UI","type":"Tag","location":{"line":1,"column":1}},{"name":"@test","type":"Tag","location":{"line":2,"column":1}}]},{"line":2,"elements":[{"start_timestamp":"2025-06-24T06:50:53.096Z","line":17,"name":"Successfully create a user with valid JSON payload","description":"","id":"create-a-user-via-api-using-post-request;successfully-create-a-user-with-valid-json-payload;;2","type":"scenario","keyword":"Scenario Outline","steps":[{"result":{"status":"passed"},"line":9,"name":"the API base URL is set","match":{"location":"Testing.stepDefs.CreateUserSteps.the_api_base_url_is_set()"},"keyword":"Given "},{"result":{"status":"passed"},"line":10,"name":"I have the JSON payload from file \"postApiData\"","match":{"arguments":[{"val":"\"postApiData\"","offset":34}],"location":"Testing.stepDefs.CreateUserSteps.i_have_the_json_payload_from_file(java.lang.String)"},"keyword":"And "},{"result":{"duration":4412000000,"status":"passed"},"line":11,"name":"I send a \"post\" request to \"/api/users\"","match":{"arguments":[{"val":"\"post\"","offset":9},{"val":"\"/api/users\"","offset":27}],"location":"Testing.stepDefs.CreateUserSteps.i_send_a_request_to(java.lang.String,java.lang.String)"},"keyword":"When "},{"result":{"status":"passed"},"line":12,"name":"the response status code should be \"201\"","match":{"arguments":[{"val":"\"201\"","offset":35}],"location":"Testing.stepDefs.CreateUserSteps.the_response_status_code_should_be(java.lang.String)"},"keyword":"Then "},{"result":{"duration":1914000000,"status":"passed"},"line":13,"name":"the response should contain a user ID ,email ,firstName ,lastName , avatar , updated At","match":{"location":"Testing.stepDefs.CreateUserSteps.the_response_should_contain_a_user_id()"},"keyword":"And "}],"tags":[{"name":"@test"}]},{"start_timestamp":"2025-06-24T06:50:59.436Z","line":28,"name":"Successfully get all users","description":"","id":"create-a-user-via-api-using-post-request;successfully-get-all-users;;2","type":"scenario","keyword":"Scenario Outline","steps":[{"result":{"status":"passed"},"line":21,"name":"the API base URL is set","match":{"location":"Testing.stepDefs.CreateUserSteps.the_api_base_url_is_set()"},"keyword":"Given "},{"result":{"duration":554000000,"status":"passed"},"line":22,"name":"I send a \"get\" request to \"/api/users/2\"","match":{"arguments":[{"val":"\"get\"","offset":9},{"val":"\"/api/users/2\"","offset":26}],"location":"Testing.stepDefs.CreateUserSteps.i_send_a_request_to(java.lang.String,java.lang.String)"},"keyword":"When "},{"result":{"status":"passed"},"line":23,"name":"the response status code should be \"200\"","match":{"arguments":[{"val":"\"200\"","offset":35}],"location":"Testing.stepDefs.CreateUserSteps.the_response_status_code_should_be(java.lang.String)"},"keyword":"Then "},{"result":{"duration":80000000,"status":"passed"},"line":24,"name":"the response should contain a user ID ,email ,firstName ,lastName , avatar , avatar","match":{"location":"Testing.stepDefs.CreateUserSteps.theResponseShouldContainAUserIDEmailFirstNameLastNameAvatarAvatar()"},"keyword":"And "}],"tags":[{"name":"@test"}]},{"start_timestamp":"2025-06-24T06:51:00.098Z","line":40,"name":"Successfully update a user with valid JSON payload","description":"","id":"create-a-user-via-api-using-post-request;successfully-update-a-user-with-valid-json-payload;;2","type":"scenario","keyword":"Scenario Outline","steps":[{"result":{"duration":1000000,"status":"passed"},"line":32,"name":"the API base URL is set","match":{"location":"Testing.stepDefs.CreateUserSteps.the_api_base_url_is_set()"},"keyword":"Given "},{"result":{"status":"passed"},"line":33,"name":"I have the JSON payload from file \"putApiData\"","match":{"arguments":[{"val":"\"putApiData\"","offset":34}],"location":"Testing.stepDefs.CreateUserSteps.i_have_the_json_payload_from_file(java.lang.String)"},"keyword":"And "},{"result":{"duration":504000000,"status":"passed"},"line":34,"name":"I send a \"put\" request to \"/api/users/2\"","match":{"arguments":[{"val":"\"put\"","offset":9},{"val":"\"/api/users/2\"","offset":26}],"location":"Testing.stepDefs.CreateUserSteps.i_send_a_request_to(java.lang.String,java.lang.String)"},"keyword":"When "},{"result":{"status":"passed"},"line":35,"name":"the response status code should be \"200\"","match":{"arguments":[{"val":"\"200\"","offset":35}],"location":"Testing.stepDefs.CreateUserSteps.the_response_status_code_should_be(java.lang.String)"},"keyword":"Then "},{"result":{"duration":50000000,"status":"passed"},"line":36,"name":"the response should contain a user ID ,email ,firstName ,lastName , avatar , updated At","match":{"location":"Testing.stepDefs.CreateUserSteps.the_response_should_contain_a_user_id()"},"keyword":"And "}],"tags":[{"name":"@test"}]}],"name":"Create a user via API using POST request","description":"  As a QA Automation Engineer\n  I want to create a user on https://reqres.in using a POST request\n  So that I can verify that user creation works as expected","id":"create-a-user-via-api-using-post-request","keyword":"Feature","uri":"file:src/main/resources/Testing/api.feature","tags":[{"name":"@test","type":"Tag","location":{"line":1,"column":1}}]}]